pipeline_sdk_test36/__init__.py
pipeline_sdk_test36/auth_service.py
pipeline_sdk_test36/inference_pipeline.py
pipeline_sdk_test36/model_inference_dsl_component.py
pipeline_sdk_test36/model_train_dsl_component.py
pipeline_sdk_test36/model_validate_dsl_component.py
pipeline_sdk_test36/pipeline_util.py
pipeline_sdk_test36/run_inference_pipeline.py
pipeline_sdk_test36/run_training_pipeline.py
pipeline_sdk_test36/run_validate_pipeline.py
pipeline_sdk_test36/train_pipeline.py
pipeline_sdk_test36/validate_pipeline.py
pipeline_sdk_test36-1.0.0.dist-info/METADATA
pipeline_sdk_test36-1.0.0.dist-info/WHEEL
pipeline_sdk_test36-1.0.0.dist-info/top_level.txt
pipeline_sdk_test36-1.0.0.dist-info/RECORD
